pycaML/__init__.py
pycaML/experiments.py
pycaML/models.py
pycaML/pycaML.py
pycaML-0.3.2.dist-info/LICENSE
pycaML-0.3.2.dist-info/METADATA
pycaML-0.3.2.dist-info/WHEEL
pycaML-0.3.2.dist-info/top_level.txt
pycaML-0.3.2.dist-info/RECORD
